[
    {
        "title": "Center for Immune Therapeutics Against Staphlyococcus Auretics",
        "name": "Aman, M",
        "appID": "1U19AI42729",
        "key": 0,
        "subItems": [
            {
                "number": "001",
                "author": "Simile, Charlie",
                "key": 1
            },
            {
                "number": "002",
                "author": "Doe, Jane",
                "key": 2
            },
            {
                "number": "003",
                "author": "Smith, John",
                "key": 3
            },
            {
                "number": "004",
                "author": "Simile Charlie",
                "key": 4
            },
            {
                "number": "005",
                "author": "Simile, Charlie",
                "key": 5
            }
        ]
    },
    {
        "title": "Lorem Ipsum Dolor Sit Amet Consecuteur",
        "name": "Aman, M",
        "appID": "1U19AI42729",
        "key": 6,
        "subItems": [
            {
                "number": "001",
                "author": "Simile, Charlie",
                "key": 7
            },
            {
                "number": "002",
                "author": "Doe, Jane",
                "key": 8
            },
            {
                "number": "003",
                "author": "Smith, John",
                "key": 9
            }
        ]
    },
    {
        "title": "Lorem Ipsum Dolor Sit Amet Consecuteur",
        "name": "Aman, M",
        "appID": "1U19AI42729",
        "key": 10,
        "subItems": [
            {
                "number": "001",
                "author": "Simile, Charlie",
                "key": 11
            },
            {
                "number": "002",
                "author": "Doe, Jane",
                "key": 12
            },
            {
                "number": "003",
                "author": "Smith, John",
                "key": 13
            },
            {
                "number": "004",
                "author": "Simile, Charlie",
                "key": 14
            },
            {
                "number": "005",
                "author": "Doe, Jane",
                "key": 15
            },
            {
                "number": "006",
                "author": "Smith, John",
                "key": 16
            },
            {
                "number": "007",
                "author": "Simile, Charlie",
                "key": 17
            },
            {
                "number": "008",
                "author": "Doe, Jane",
                "key": 18
            },
            {
                "number": "009",
                "author": "Smith, John",
                "key": 19
            },
            {
                "number": "010",
                "author": "Simile, Charlie",
                "key": 20
            },
            {
                "number": "011",
                "author": "Doe, Jane",
                "key": 21
            },
            {
                "number": "012",
                "author": "Smith, John",
                "key": 22
            },
            {
                "number": "013",
                "author": "Simile, Charlie",
                "key": 23
            },
            {
                "number": "014",
                "author": "Doe, Jane",
                "key": 24
            },
            {
                "number": "015",
                "author": "Smith, John",
                "key": 25
            }
        ]
    }
]